{
    "key": "group_59804d1f07a93",
    "title": "Testimonial Option",
    "fields": [
        {
            "post_type": [
                "program_gender"
            ],
            "taxonomy": [],
            "allow_null": 0,
            "multiple": 0,
            "return_format": "id",
            "ui": 1,
            "key": "field_59804d2b6ffec",
            "label": "Select Gender",
            "name": "select_gender",
            "type": "post_object",
            "instructions": "",
            "required": 0,
            "conditional_logic": 0,
            "wrapper": {
                "width": "",
                "class": "",
                "id": ""
            }
        }
    ],
    "location": [
        [
            {
                "param": "post_type",
                "operator": "==",
                "value": "testimonial"
            }
        ]
    ],
    "menu_order": 0,
    "position": "normal",
    "style": "default",
    "label_placement": "top",
    "instruction_placement": "label",
    "hide_on_screen": "",
    "active": 1,
    "description": "",
    "modified": 1501580633
}